nonebot_plugin_BiliRequestAll/__init__.py
nonebot_plugin_BiliRequestAll/api.py
nonebot_plugin_BiliRequestAll/func.py
nonebot_plugin_BiliRequestAll/log.py
Shadow403-0.2.6.dist-info/LICENSE
Shadow403-0.2.6.dist-info/METADATA
Shadow403-0.2.6.dist-info/WHEEL
Shadow403-0.2.6.dist-info/top_level.txt
Shadow403-0.2.6.dist-info/RECORD
