Metadata-Version: 2.1
Name: Shadow403
Version: 0.2.6
Summary: Use Medal Support Join QQ Group
Home-page: https://github.com/Shadow403/nonebot_plugin_BiliRequestAll
Author: Shadow403
Author-email: anonymous_hax@foxmail.com
Classifier: Programming Language :: Python :: 3.11
Classifier: License :: OSI Approved :: MIT License
Classifier: Operating System :: OS Independent
Requires-Python: >=3.10
License-File: LICENSE
Requires-Dist: nonebot2 >=2.0.0
Requires-Dist: nonebot-adapter-onebot >=2.2.3
Requires-Dist: requests >=2.31.0
